faostat/__init__.py
faostat/faostat.py
faostat-1.1.2.dist-info/LICENSE.txt
faostat-1.1.2.dist-info/METADATA
faostat-1.1.2.dist-info/WHEEL
faostat-1.1.2.dist-info/top_level.txt
faostat-1.1.2.dist-info/RECORD
