Metadata-Version: 2.1
Name: faostat
Version: 1.1.2
Summary: Faostat Python Package
Author: Noemi Emanuela Cazzaniga
Author-email: noemi.cazzaniga@polimi.it
License: MIT
Project-URL: Source, https://bitbucket.org/noemicazzaniga/faostat/src/master/
Keywords: faostat statistics data economics science
Classifier: Development Status :: 5 - Production/Stable
Classifier: Operating System :: OS Independent
Classifier: Programming Language :: Python :: 3
Classifier: License :: OSI Approved :: MIT License
Classifier: Intended Audience :: Developers
Classifier: Intended Audience :: Financial and Insurance Industry
Classifier: Intended Audience :: Science/Research
Classifier: Topic :: Office/Business
Classifier: Topic :: Office/Business :: Financial
Classifier: Topic :: Scientific/Engineering
Classifier: Topic :: Scientific/Engineering :: Information Analysis
Classifier: Topic :: Utilities
Requires-Python: >=3.6
License-File: LICENSE.txt
Requires-Dist: pandas
Requires-Dist: requests
